aat_poc/AE_Sim.py
aat_poc/CredentialServer.py
aat_poc/SFC_Sim.py
aat_poc/__init__.py
aat_poc/ae_key_request.py
aat_poc/link.py
aat_poc-0.1.dist-info/METADATA
aat_poc-0.1.dist-info/WHEEL
aat_poc-0.1.dist-info/top_level.txt
aat_poc-0.1.dist-info/zip-safe
aat_poc-0.1.dist-info/RECORD
