Metadata-Version: 2.1
Name: aat-poc
Version: 0.1
Summary: AAT proof of concept
Home-page: UNKNOWN
Author: Debo Akeredolu
Author-email: debola31@gmail.com
License: MIT
Platform: UNKNOWN
Requires-Dist: requests
Requires-Dist: cryptography
Requires-Dist: datetime
Requires-Dist: flask
